qasync/__init__.py
qasync/_common.py
qasync/_unix.py
qasync/_windows.py
qasync-0.27.0.dist-info/LICENSE
qasync-0.27.0.dist-info/METADATA
qasync-0.27.0.dist-info/WHEEL
qasync-0.27.0.dist-info/RECORD
