Metadata-Version: 2.1
Name: qasync
Version: 0.27.0
Summary: Python library for using asyncio in Qt-based applications
Home-page: https://github.com/CabbageDevelopment/qasync
License: BSD-2-Clause
Keywords: Qt,asncio
Author: Arve Knudsen
Author-email: arve.knudsen@gmail.com
Maintainer: Alex March
Maintainer-email: alexmach@fastmail.com
Requires-Python: >=3.8,<4.0
Classifier: Development Status :: 4 - Beta
Classifier: Environment :: X11 Applications :: Qt
Classifier: Intended Audience :: Developers
Classifier: License :: OSI Approved :: BSD License
Classifier: Operating System :: MacOS
Classifier: Operating System :: Microsoft
Classifier: Operating System :: POSIX
Classifier: Programming Language :: Python :: 3
Classifier: Programming Language :: Python :: 3.8
Classifier: Programming Language :: Python :: 3.9
Classifier: Programming Language :: Python :: 3.10
Classifier: Programming Language :: Python :: 3.11
Classifier: Programming Language :: Python :: 3.12
Classifier: Topic :: Software Development :: Libraries :: Python Modules
Project-URL: Repository, https://github.com/CabbageDevelopment/qasync
